setup.py
Login/__init__.py
Login/reg.py
VAClogin.egg-info/PKG-INFO
VAClogin.egg-info/SOURCES.txt
VAClogin.egg-info/dependency_links.txt
VAClogin.egg-info/top_level.txt