Metadata-Version: 2.1
Name: VAClogin
Version: 0.0.1
Summary: 这是一个登陆和注册的外部库
Home-page: UNKNOWN
Author: Wind
Author-email: jinghaozhehh@163.com
License: UNKNOWN
Platform: UNKNOWN
Classifier: Programming Language :: Python :: 3
Classifier: License :: OSI Approved :: MIT License
Classifier: Operating System :: OS Independent
